{
    "character": "Gordito",
    "fighting_styles": {
        "archer": 0,
        "berserker": 0,
        "bowfighter": 0,
        "champion": 0,
        "dirty_fighter": 0,
        "fencer": 0,
        "gunslinger": 0,
        "monster_hunter": 0,
        "sand_dancer": 0,
        "shieldbearer": 0,
        "wood_walker": 0
    },
    "heritage": "",
    "items": [
        "item_1",
        "item_2",
        "item_3"
    ],
    "race": "Gorgo",
    "rp_attributes": {
        "age": 20,
        "background": "",
        "eyes": "eye colour",
        "hair": "hair colour",
        "height": "height",
        "image": "C:/Users/Cameron/Documents/code/abril-theia-character-gen/images/download (3).png",
        "languages": [
            "language 1",
            "language 2"
        ],
        "name": "name",
        "notes": "",
        "skin": "skin colour",
        "weight": "weight"
    },
    "skills": {
        "Animal handling": {
            "manual": 0,
            "proficiency": 0,
            "stat": "Wisdom",
            "value": -1
        },
        "Athletics": {
            "manual": 0,
            "proficiency": 0,
            "stat": "Strength",
            "value": 3
        },
        "Diplomacy": {
            "manual": 0,
            "proficiency": 0,
            "stat": "Charisma",
            "value": -3
        },
        "Geography": {
            "manual": 0,
            "proficiency": 0,
            "stat": "Intelligence",
            "value": 3
        },
        "History": {
            "manual": 0,
            "proficiency": 0,
            "stat": "Intelligence",
            "value": 3
        },
        "Insight": {
            "manual": 0,
            "proficiency": 0,
            "stat": "Intelligence",
            "value": 3
        },
        "Intimidation": {
            "manual": 0,
            "proficiency": 0,
            "stat": "Charisma",
            "value": -3
        },
        "Ley Lore": {
            "manual": 0,
            "proficiency": 0,
            "stat": "Charisma",
            "value": -3
        },
        "Medicine": {
            "manual": 0,
            "proficiency": 0,
            "stat": "Intelligence",
            "value": 3
        },
        "Nature": {
            "manual": 0,
            "proficiency": 0,
            "stat": "Intelligence",
            "value": 3
        },
        "Perception": {
            "manual": 0,
            "proficiency": 0,
            "stat": "Wisdom",
            "value": -1
        },
        "Performance": {
            "manual": 0,
            "proficiency": 0,
            "stat": "Charisma",
            "value": -3
        },
        "Profession 1": {
            "manual": 0,
            "proficiency": 0,
            "stat": "Strength",
            "value": 3
        },
        "Profession 2": {
            "manual": 0,
            "proficiency": 0,
            "stat": "Dexterity",
            "value": -2
        },
        "Profession 3": {
            "manual": 0,
            "proficiency": 0,
            "stat": "Constitution",
            "value": 3
        },
        "Religion": {
            "manual": 0,
            "proficiency": 0,
            "stat": "Intelligence",
            "value": 3
        },
        "Riding": {
            "manual": 0,
            "proficiency": 0,
            "stat": "Dexterity",
            "value": -2
        },
        "Stealth": {
            "manual": 0,
            "proficiency": 0,
            "stat": "Dexterity",
            "value": -2
        },
        "Subtlety": {
            "manual": 0,
            "proficiency": 0,
            "stat": "Intelligence",
            "value": 3
        }
    },
    "stats": {
        "STAT:AC": 10,
        "STAT:CHA": 4,
        "STAT:CON": 16,
        "STAT:DEX": 6,
        "STAT:HP": 8,
        "STAT:INIT": 0,
        "STAT:INT": 15,
        "STAT:MOR": 30,
        "STAT:PROF": 2,
        "STAT:RES": 0,
        "STAT:SPD": 30,
        "STAT:STR": 16,
        "STAT:WIS": 8
    },
    "traits": {
        "leymancy": [],
        "martial": [],
        "profession": [],
        "subtlety": []
    }
}